diplo_locus/__init__.py
diplo_locus/diffusion_core.py
diplo_locus/likelihood.py
diplo_locus/simulate.py
diplo_locus/utility.py
diplo_locus-1.1.2.data/scripts/DiploLocus.py
diplo_locus-1.1.2.data/scripts/DiploLocus_likelihood.py
diplo_locus-1.1.2.data/scripts/DiploLocus_simulate.py
src/README.md
src/__init__.py
src/diffusion_core.py
src/likelihood.py
src/simulate.py
src/utility.py
diplo_locus-1.1.2.dist-info/LICENSE
diplo_locus-1.1.2.dist-info/METADATA
diplo_locus-1.1.2.dist-info/WHEEL
diplo_locus-1.1.2.dist-info/entry_points.txt
diplo_locus-1.1.2.dist-info/top_level.txt
diplo_locus-1.1.2.dist-info/RECORD
