Metadata-Version: 2.1
Name: diplo-locus
Version: 1.1.2
Summary: Light-weight toolkit for the inference and simulation of Wright-Fisher diploid selection on independent loci from time-series data.
Home-page: https://github.com/steinrue/diplo_locus
License: MIT
Requires-Python: >=3.8
License-File: LICENSE
Requires-Dist: numpy
Requires-Dist: scipy
Requires-Dist: pandas
Requires-Dist: matplotlib
Requires-Dist: scikit-allel
